{
  "coupons": {
    "metadata": {
      "isin": {
        "type": "string",
        "bytes": 765,
        "max_size": 0
      },
      "name": {
        "type": "string",
        "bytes": 765,
        "max_size": 0
      },
      "issuevalue": {
        "type": "double"
      },
      "coupondate": {
        "type": "date",
        "bytes": 10,
        "max_size": 0
      },
      "recorddate": {
        "type": "date",
        "bytes": 10,
        "max_size": 0
      },
      "startdate": {
        "type": "date",
        "bytes": 10,
        "max_size": 0
      },
      "initialfacevalue": {
        "type": "double"
      },
      "facevalue": {
        "type": "double"
      },
      "faceunit": {
        "type": "string",
        "bytes": 9,
        "max_size": 0
      },
      "value": {
        "type": "double"
      },
      "valueprc": {
        "type": "double"
      },
      "value_rub": {
        "type": "double"
      }
    },
    "columns": [
      "isin",
      "name",
      "issuevalue",
      "coupondate",
      "recorddate",
      "startdate",
      "initialfacevalue",
      "facevalue",
      "faceunit",
      "value",
      "valueprc",
      "value_rub"
    ],
    "data": [
      [
        "RU000A0JRDY3",
        "\u0414\u041e\u041c.\u0420\u0424 (\u0410\u041e) \u043e\u0431\u043b. \u0441\u0435\u0440.\u041018",
        7000000000,
        "2011-04-15",
        "2011-04-06",
        "2011-04-05",
        1000,
        1000,
        "RUB",
        2.19,
        8,
        2.19
      ],
      [
        "RU000A0JRDY3",
        "\u0414\u041e\u041c.\u0420\u0424 (\u0410\u041e) \u043e\u0431\u043b. \u0441\u0435\u0440.\u041018",
        7000000000,
        "2011-07-15",
        "2011-07-06",
        "2011-04-15",
        1000,
        1000,
        "RUB",
        19.95,
        8,
        19.95
      ],
      [
        "RU000A0JRDY3",
        "\u0414\u041e\u041c.\u0420\u0424 (\u0410\u041e) \u043e\u0431\u043b. \u0441\u0435\u0440.\u041018",
        7000000000,
        "2011-10-15",
        "2011-10-06",
        "2011-07-15",
        1000,
        1000,
        "RUB",
        20.16,
        8,
        20.16
      ],
      [
        "RU000A0JRDY3",
        "\u0414\u041e\u041c.\u0420\u0424 (\u0410\u041e) \u043e\u0431\u043b. \u0441\u0435\u0440.\u041018",
        7000000000,
        "2012-01-15",
        "2011-12-28",
        "2011-10-17",
        1000,
        1000,
        "RUB",
        20.16,
        8,
        20.16
      ],
      [
        "RU000A0JRDY3",
        "\u0414\u041e\u041c.\u0420\u0424 (\u0410\u041e) \u043e\u0431\u043b. \u0441\u0435\u0440.\u041018",
        7000000000,
        "2012-04-15",
        "2012-04-05",
        "2012-01-16",
        1000,
        1000,
        "RUB",
        19.95,
        8,
        19.95
      ],
      [
        "RU000A0JRDY3",
        "\u0414\u041e\u041c.\u0420\u0424 (\u0410\u041e) \u043e\u0431\u043b. \u0441\u0435\u0440.\u041018",
        7000000000,
        "2012-07-15",
        "2012-07-05",
        "2012-04-16",
        1000,
        1000,
        "RUB",
        19.95,
        8,
        19.95
      ],
      [
        "RU000A0JRDY3",
        "\u0414\u041e\u041c.\u0420\u0424 (\u0410\u041e) \u043e\u0431\u043b. \u0441\u0435\u0440.\u041018",
        7000000000,
        "2012-10-15",
        "2012-10-04",
        "2012-07-16",
        1000,
        1000,
        "RUB",
        20.16,
        8,
        20.16
      ],
      [
        "RU000A0JRDY3",
        "\u0414\u041e\u041c.\u0420\u0424 (\u0410\u041e) \u043e\u0431\u043b. \u0441\u0435\u0440.\u041018",
        7000000000,
        "2013-01-15",
        "2012-12-27",
        "2012-10-15",
        1000,
        1000,
        "RUB",
        20.16,
        8,
        20.16
      ],
      [
        "RU000A0JRDY3",
        "\u0414\u041e\u041c.\u0420\u0424 (\u0410\u041e) \u043e\u0431\u043b. \u0441\u0435\u0440.\u041018",
        7000000000,
        "2013-04-15",
        "2013-04-04",
        "2013-01-15",
        1000,
        1000,
        "RUB",
        19.73,
        8,
        19.73
      ],
      [
        "RU000A0JRDY3",
        "\u0414\u041e\u041c.\u0420\u0424 (\u0410\u041e) \u043e\u0431\u043b. \u0441\u0435\u0440.\u041018",
        7000000000,
        "2013-07-15",
        "2013-07-04",
        "2013-04-15",
        1000,
        1000,
        "RUB",
        19.95,
        8,
        19.95
      ],
      [
        "RU000A0JRDY3",
        "\u0414\u041e\u041c.\u0420\u0424 (\u0410\u041e) \u043e\u0431\u043b. \u0441\u0435\u0440.\u041018",
        7000000000,
        "2013-10-15",
        "2013-10-06",
        "2013-07-15",
        1000,
        1000,
        "RUB",
        20.16,
        8,
        20.16
      ],
      [
        "RU000A0JRDY3",
        "\u0414\u041e\u041c.\u0420\u0424 (\u0410\u041e) \u043e\u0431\u043b. \u0441\u0435\u0440.\u041018",
        7000000000,
        "2014-01-15",
        "2014-01-06",
        "2013-10-15",
        1000,
        1000,
        "RUB",
        20.16,
        8,
        20.16
      ],
      [
        "RU000A0JRDY3",
        "\u0414\u041e\u041c.\u0420\u0424 (\u0410\u041e) \u043e\u0431\u043b. \u0441\u0435\u0440.\u041018",
        7000000000,
        "2014-04-15",
        "2014-04-06",
        "2014-01-15",
        1000,
        1000,
        "RUB",
        19.73,
        8,
        19.73
      ],
      [
        "RU000A0JRDY3",
        "\u0414\u041e\u041c.\u0420\u0424 (\u0410\u041e) \u043e\u0431\u043b. \u0441\u0435\u0440.\u041018",
        7000000000,
        "2014-07-15",
        "2014-07-06",
        "2014-04-15",
        1000,
        1000,
        "RUB",
        19.95,
        8,
        19.95
      ],
      [
        "RU000A0JRDY3",
        "\u0414\u041e\u041c.\u0420\u0424 (\u0410\u041e) \u043e\u0431\u043b. \u0441\u0435\u0440.\u041018",
        7000000000,
        "2014-10-15",
        "2014-10-06",
        "2014-07-15",
        1000,
        1000,
        "RUB",
        20.16,
        8,
        20.16
      ],
      [
        "RU000A0JRDY3",
        "\u0414\u041e\u041c.\u0420\u0424 (\u0410\u041e) \u043e\u0431\u043b. \u0441\u0435\u0440.\u041018",
        7000000000,
        "2015-01-15",
        "2015-01-06",
        "2014-10-15",
        1000,
        1000,
        "RUB",
        20.16,
        8,
        20.16
      ],
      [
        "RU000A0JRDY3",
        "\u0414\u041e\u041c.\u0420\u0424 (\u0410\u041e) \u043e\u0431\u043b. \u0441\u0435\u0440.\u041018",
        7000000000,
        "2015-04-15",
        "2015-04-06",
        "2015-01-15",
        1000,
        1000,
        "RUB",
        19.73,
        8,
        19.73
      ],
      [
        "RU000A0JRDY3",
        "\u0414\u041e\u041c.\u0420\u0424 (\u0410\u041e) \u043e\u0431\u043b. \u0441\u0435\u0440.\u041018",
        7000000000,
        "2015-07-15",
        "2015-07-06",
        "2015-04-15",
        1000,
        1000,
        "RUB",
        19.95,
        8,
        19.95
      ],
      [
        "RU000A0JRDY3",
        "\u0414\u041e\u041c.\u0420\u0424 (\u0410\u041e) \u043e\u0431\u043b. \u0441\u0435\u0440.\u041018",
        7000000000,
        "2015-10-15",
        "2015-10-06",
        "2015-07-15",
        1000,
        1000,
        "RUB",
        20.16,
        8,
        20.16
      ],
      [
        "RU000A0JRDY3",
        "\u0414\u041e\u041c.\u0420\u0424 (\u0410\u041e) \u043e\u0431\u043b. \u0441\u0435\u0440.\u041018",
        7000000000,
        "2016-01-15",
        "2015-12-29",
        "2015-10-15",
        1000,
        1000,
        "RUB",
        20.16,
        8,
        20.16
      ]
    ]
  },
  "amortizations": {
    "metadata": {
      "isin": {
        "type": "string",
        "bytes": 765,
        "max_size": 0
      },
      "name": {
        "type": "string",
        "bytes": 765,
        "max_size": 0
      },
      "issuevalue": {
        "type": "double"
      },
      "amortdate": {
        "type": "date",
        "bytes": 10,
        "max_size": 0
      },
      "facevalue": {
        "type": "double"
      },
      "initialfacevalue": {
        "type": "double"
      },
      "faceunit": {
        "type": "string",
        "bytes": 9,
        "max_size": 0
      },
      "valueprc": {
        "type": "double"
      },
      "value": {
        "type": "double"
      },
      "value_rub": {
        "type": "double"
      },
      "data_source": {
        "type": "string",
        "bytes": 36,
        "max_size": 0
      }
    },
    "columns": [
      "isin",
      "name",
      "issuevalue",
      "amortdate",
      "facevalue",
      "initialfacevalue",
      "faceunit",
      "valueprc",
      "value",
      "value_rub",
      "data_source"
    ],
    "data": [
      [
        "RU000A0JRDY3",
        "\u0414\u041e\u041c.\u0420\u0424 (\u0410\u041e) \u043e\u0431\u043b. \u0441\u0435\u0440.\u041018",
        7000000000,
        "2020-07-15",
        1000,
        1000,
        "RUB",
        30.0,
        300,
        300,
        "amortization"
      ],
      [
        "RU000A0JRDY3",
        "\u0414\u041e\u041c.\u0420\u0424 (\u0410\u041e) \u043e\u0431\u043b. \u0441\u0435\u0440.\u041018",
        7000000000,
        "2021-07-15",
        1000,
        1000,
        "RUB",
        20.0,
        200,
        200,
        "amortization"
      ],
      [
        "RU000A0JRDY3",
        "\u0414\u041e\u041c.\u0420\u0424 (\u0410\u041e) \u043e\u0431\u043b. \u0441\u0435\u0440.\u041018",
        7000000000,
        "2022-07-15",
        1000,
        1000,
        "RUB",
        20.0,
        200,
        200,
        "amortization"
      ],
      [
        "RU000A0JRDY3",
        "\u0414\u041e\u041c.\u0420\u0424 (\u0410\u041e) \u043e\u0431\u043b. \u0441\u0435\u0440.\u041018",
        7000000000,
        "2023-07-15",
        1000,
        1000,
        "RUB",
        30.0,
        300,
        300,
        "amortization"
      ]
    ]
  }
}